[
 {
  "id": "P_Pulmonary_regurgitation_1.wav",
  "bodySpot": "Pulmonic area",
  "segmenation": {
   "S1": [],
   "S2": [],
   "syslole": [],
   "diastole": [],
   "unsegmentable": [
    {
     "start": "0.000",
     "end": "3.966"
    }
   ]
  },
  "systolicMurmurs": false,
  "diastolicMurmurs": false,
  "constantMurmurs": false
 },
 {
  "id": "P_Pulmonary_regurgitation_11.wav",
  "bodySpot": "Pulmonic area",
  "segmenation": {
   "S1": [
    {
     "start": "0.737",
     "end": "0.814"
    },
    {
     "start": "1.703",
     "end": "1.777"
    },
    {
     "start": "2.665",
     "end": "2.742"
    },
    {
     "start": "3.632",
     "end": "3.709"
    },
    {
     "start": "4.627",
     "end": "4.701"
    },
    {
     "start": "5.632",
     "end": "5.707"
    },
    {
     "start": "6.619",
     "end": "6.691"
    },
    {
     "start": "7.596",
     "end": "7.670"
    },
    {
     "start": "8.609",
     "end": "8.687"
    },
    {
     "start": "9.602",
     "end": "9.684"
    },
    {
     "start": "10.574",
     "end": "10.657"
    },
    {
     "start": "11.547",
     "end": "11.626"
    },
    {
     "start": "12.512",
     "end": "12.598"
    },
    {
     "start": "13.295",
     "end": "13.380"
    },
    {
     "start": "14.267",
     "end": "14.344"
    },
    {
     "start": "15.259",
     "end": "15.345"
    },
    {
     "start": "16.260",
     "end": "16.329"
    },
    {
     "start": "17.228",
     "end": "17.306"
    },
    {
     "start": "18.218",
     "end": "18.295"
    },
    {
     "start": "19.180",
     "end": "19.258"
    },
    {
     "start": "20.139",
     "end": "20.215"
    }
   ],
   "S2": [
    {
     "start": "0.101",
     "end": "0.181"
    },
    {
     "start": "1.062",
     "end": "1.138"
    },
    {
     "start": "2.013",
     "end": "2.089"
    },
    {
     "start": "2.979",
     "end": "3.068"
    },
    {
     "start": "3.964",
     "end": "4.041"
    },
    {
     "start": "4.946",
     "end": "5.025"
    },
    {
     "start": "5.946",
     "end": "6.026"
    },
    {
     "start": "6.929",
     "end": "7.006"
    },
    {
     "start": "7.914",
     "end": "7.990"
    },
    {
     "start": "8.925",
     "end": "9.003"
    },
    {
     "start": "9.920",
     "end": "9.999"
    },
    {
     "start": "10.892",
     "end": "10.972"
    },
    {
     "start": "11.849",
     "end": "11.935"
    },
    {
     "start": "12.826",
     "end": "12.912"
    },
    {
     "start": "13.610",
     "end": "13.692"
    },
    {
     "start": "14.573",
     "end": "14.661"
    },
    {
     "start": "15.573",
     "end": "15.656"
    },
    {
     "start": "16.568",
     "end": "16.643"
    },
    {
     "start": "17.561",
     "end": "17.638"
    },
    {
     "start": "18.530",
     "end": "18.609"
    },
    {
     "start": "19.484",
     "end": "19.563"
    },
    {
     "start": "20.447",
     "end": "20.525"
    }
   ],
   "syslole": [],
   "diastole": [],
   "unsegmentable": []
  },
  "systolicMurmurs": true,
  "diastolicMurmurs": true,
  "constantMurmurs": false
 },
 {
  "id": "P_Pulmonary_regurgitation_12.wav",
  "bodySpot": "Pulmonic area",
  "segmenation": {
   "S1": [
    {
     "start": "0.122",
     "end": "0.203"
    },
    {
     "start": "1.085",
     "end": "1.166"
    },
    {
     "start": "2.057",
     "end": "2.137"
    },
    {
     "start": "3.054",
     "end": "3.140"
    },
    {
     "start": "4.050",
     "end": "4.130"
    },
    {
     "start": "5.041",
     "end": "5.119"
    },
    {
     "start": "6.023",
     "end": "6.101"
    },
    {
     "start": "7.032",
     "end": "7.114"
    },
    {
     "start": "8.027",
     "end": "8.106"
    },
    {
     "start": "9.003",
     "end": "9.091"
    },
    {
     "start": "9.966",
     "end": "10.051"
    },
    {
     "start": "10.947",
     "end": "11.023"
    },
    {
     "start": "11.728",
     "end": "11.807"
    },
    {
     "start": "12.689",
     "end": "12.771"
    },
    {
     "start": "13.686",
     "end": "13.772"
    },
    {
     "start": "14.681",
     "end": "14.765"
    },
    {
     "start": "15.653",
     "end": "15.734"
    },
    {
     "start": "16.632",
     "end": "16.713"
    },
    {
     "start": "17.605",
     "end": "17.692"
    },
    {
     "start": "18.565",
     "end": "18.644"
    },
    {
     "start": "19.525",
     "end": "19.605"
    },
    {
     "start": "20.518",
     "end": "20.584"
    }
   ],
   "S2": [
    {
     "start": "0.440",
     "end": "0.514"
    },
    {
     "start": "1.407",
     "end": "1.485"
    },
    {
     "start": "2.385",
     "end": "2.465"
    },
    {
     "start": "3.370",
     "end": "3.453"
    },
    {
     "start": "4.363",
     "end": "4.443"
    },
    {
     "start": "5.354",
     "end": "5.439"
    },
    {
     "start": "6.342",
     "end": "6.425"
    },
    {
     "start": "7.351",
     "end": "7.432"
    },
    {
     "start": "8.342",
     "end": "8.429"
    },
    {
     "start": "9.318",
     "end": "9.398"
    },
    {
     "start": "10.280",
     "end": "10.361"
    },
    {
     "start": "11.259",
     "end": "11.339"
    },
    {
     "start": "12.038",
     "end": "12.115"
    },
    {
     "start": "13.000",
     "end": "13.089"
    },
    {
     "start": "13.999",
     "end": "14.082"
    },
    {
     "start": "14.999",
     "end": "15.082"
    },
    {
     "start": "15.978",
     "end": "16.058"
    },
    {
     "start": "16.961",
     "end": "17.047"
    },
    {
     "start": "17.912",
     "end": "17.995"
    },
    {
     "start": "18.869",
     "end": "18.948"
    },
    {
     "start": "19.841",
     "end": "19.928"
    }
   ],
   "syslole": [
    {
     "start": "0.203",
     "end": "0.440"
    },
    {
     "start": "1.166",
     "end": "1.407"
    },
    {
     "start": "2.137",
     "end": "2.385"
    },
    {
     "start": "3.140",
     "end": "3.370"
    },
    {
     "start": "4.130",
     "end": "4.363"
    },
    {
     "start": "5.119",
     "end": "5.354"
    },
    {
     "start": "6.101",
     "end": "6.342"
    },
    {
     "start": "7.114",
     "end": "7.351"
    },
    {
     "start": "8.106",
     "end": "8.342"
    },
    {
     "start": "9.091",
     "end": "9.318"
    },
    {
     "start": "10.051",
     "end": "10.280"
    },
    {
     "start": "11.023",
     "end": "11.259"
    },
    {
     "start": "11.807",
     "end": "12.038"
    },
    {
     "start": "12.771",
     "end": "13.000"
    },
    {
     "start": "13.772",
     "end": "13.999"
    },
    {
     "start": "14.765",
     "end": "14.999"
    },
    {
     "start": "15.734",
     "end": "15.978"
    },
    {
     "start": "16.713",
     "end": "16.961"
    },
    {
     "start": "17.692",
     "end": "17.912"
    },
    {
     "start": "18.644",
     "end": "18.869"
    },
    {
     "start": "19.605",
     "end": "19.841"
    }
   ],
   "diastole": [
    {
     "start": "0.514",
     "end": "1.085"
    },
    {
     "start": "1.485",
     "end": "2.057"
    },
    {
     "start": "2.465",
     "end": "3.054"
    },
    {
     "start": "3.453",
     "end": "4.050"
    },
    {
     "start": "4.443",
     "end": "5.041"
    },
    {
     "start": "5.439",
     "end": "6.023"
    },
    {
     "start": "6.425",
     "end": "7.032"
    },
    {
     "start": "7.432",
     "end": "8.027"
    },
    {
     "start": "8.429",
     "end": "9.003"
    },
    {
     "start": "9.398",
     "end": "9.966"
    },
    {
     "start": "10.361",
     "end": "10.947"
    },
    {
     "start": "11.339",
     "end": "11.728"
    },
    {
     "start": "12.115",
     "end": "12.689"
    },
    {
     "start": "13.089",
     "end": "13.686"
    },
    {
     "start": "14.082",
     "end": "14.681"
    },
    {
     "start": "15.082",
     "end": "15.653"
    },
    {
     "start": "16.058",
     "end": "16.632"
    },
    {
     "start": "17.047",
     "end": "17.605"
    },
    {
     "start": "17.995",
     "end": "18.565"
    },
    {
     "start": "18.948",
     "end": "19.525"
    },
    {
     "start": "19.928",
     "end": "20.518"
    }
   ],
   "unsegmentable": [
    {
     "start": "0.000",
     "end": "0.122"
    }
   ]
  },
  "systolicMurmurs": true,
  "diastolicMurmurs": true,
  "constantMurmurs": false
 },
 {
  "id": "P_Pulmonary_regurgitation_13.wav",
  "bodySpot": "Pulmonic area",
  "segmenation": {
   "S1": [
    {
     "start": "0.211",
     "end": "0.291"
    },
    {
     "start": "1.178",
     "end": "1.254"
    },
    {
     "start": "2.167",
     "end": "2.252"
    },
    {
     "start": "3.917",
     "end": "3.994"
    },
    {
     "start": "4.909",
     "end": "4.984"
    },
    {
     "start": "5.897",
     "end": "5.977"
    },
    {
     "start": "6.899",
     "end": "6.987"
    },
    {
     "start": "7.897",
     "end": "7.977"
    },
    {
     "start": "8.866",
     "end": "8.956"
    },
    {
     "start": "9.838",
     "end": "9.922"
    },
    {
     "start": "10.807",
     "end": "10.896"
    },
    {
     "start": "11.574",
     "end": "11.660"
    },
    {
     "start": "12.549",
     "end": "12.626"
    },
    {
     "start": "13.556",
     "end": "13.633"
    },
    {
     "start": "14.535",
     "end": "14.619"
    },
    {
     "start": "15.526",
     "end": "15.604"
    },
    {
     "start": "16.499",
     "end": "16.579"
    },
    {
     "start": "17.475",
     "end": "17.555"
    },
    {
     "start": "18.428",
     "end": "18.511"
    },
    {
     "start": "19.391",
     "end": "19.472"
    },
    {
     "start": "20.359",
     "end": "20.438"
    }
   ],
   "S2": [
    {
     "start": "0.523",
     "end": "0.607"
    },
    {
     "start": "1.487",
     "end": "1.570"
    },
    {
     "start": "2.484",
     "end": "2.564"
    },
    {
     "start": "4.233",
     "end": "4.313"
    },
    {
     "start": "5.217",
     "end": "5.301"
    },
    {
     "start": "6.212",
     "end": "6.293"
    },
    {
     "start": "7.217",
     "end": "7.299"
    },
    {
     "start": "8.209",
     "end": "8.292"
    },
    {
     "start": "9.185",
     "end": "9.264"
    },
    {
     "start": "10.154",
     "end": "10.241"
    },
    {
     "start": "11.120",
     "end": "11.206"
    },
    {
     "start": "11.904",
     "end": "11.991"
    },
    {
     "start": "12.867",
     "end": "12.948"
    },
    {
     "start": "13.865",
     "end": "13.948"
    },
    {
     "start": "14.858",
     "end": "14.935"
    },
    {
     "start": "15.849",
     "end": "15.929"
    },
    {
     "start": "16.825",
     "end": "16.908"
    },
    {
     "start": "17.787",
     "end": "17.867"
    },
    {
     "start": "18.738",
     "end": "18.817"
    },
    {
     "start": "19.705",
     "end": "19.790"
    }
   ],
   "syslole": [
    {
     "start": "0.291",
     "end": "0.523"
    },
    {
     "start": "1.254",
     "end": "1.487"
    },
    {
     "start": "2.252",
     "end": "2.484"
    },
    {
     "start": "3.994",
     "end": "4.233"
    },
    {
     "start": "4.984",
     "end": "5.217"
    },
    {
     "start": "5.977",
     "end": "6.212"
    },
    {
     "start": "6.987",
     "end": "7.217"
    },
    {
     "start": "7.977",
     "end": "8.209"
    },
    {
     "start": "8.956",
     "end": "9.185"
    },
    {
     "start": "9.922",
     "end": "10.154"
    },
    {
     "start": "10.896",
     "end": "11.120"
    },
    {
     "start": "11.660",
     "end": "11.904"
    },
    {
     "start": "12.626",
     "end": "12.867"
    },
    {
     "start": "13.633",
     "end": "13.865"
    },
    {
     "start": "14.619",
     "end": "14.858"
    },
    {
     "start": "15.604",
     "end": "15.849"
    },
    {
     "start": "16.579",
     "end": "16.825"
    },
    {
     "start": "17.555",
     "end": "17.787"
    },
    {
     "start": "18.511",
     "end": "18.738"
    },
    {
     "start": "19.472",
     "end": "19.705"
    }
   ],
   "diastole": [
    {
     "start": "0.607",
     "end": "1.178"
    },
    {
     "start": "1.570",
     "end": "2.167"
    },
    {
     "start": "4.313",
     "end": "4.909"
    },
    {
     "start": "5.301",
     "end": "5.897"
    },
    {
     "start": "6.293",
     "end": "6.899"
    },
    {
     "start": "7.299",
     "end": "7.897"
    },
    {
     "start": "8.292",
     "end": "8.866"
    },
    {
     "start": "9.264",
     "end": "9.838"
    },
    {
     "start": "10.241",
     "end": "10.807"
    },
    {
     "start": "11.206",
     "end": "11.574"
    },
    {
     "start": "11.991",
     "end": "12.549"
    },
    {
     "start": "12.948",
     "end": "13.556"
    },
    {
     "start": "13.948",
     "end": "14.535"
    },
    {
     "start": "14.935",
     "end": "15.526"
    },
    {
     "start": "15.929",
     "end": "16.499"
    },
    {
     "start": "16.908",
     "end": "17.475"
    },
    {
     "start": "17.867",
     "end": "18.428"
    },
    {
     "start": "18.817",
     "end": "19.391"
    },
    {
     "start": "19.790",
     "end": "20.359"
    }
   ],
   "unsegmentable": [
    {
     "start": "0.000",
     "end": "0.211"
    },
    {
     "start": "20.438",
     "end": "20.573"
    },
    {
     "start": "2.564",
     "end": "3.917"
    }
   ]
  },
  "systolicMurmurs": true,
  "diastolicMurmurs": true,
  "constantMurmurs": false
 },
 {
  "id": "P_Pulmonary_regurgitation_14.wav",
  "bodySpot": "Pulmonic area",
  "segmenation": {
   "S1": [
    {
     "start": "0.690",
     "end": "0.780"
    },
    {
     "start": "1.680",
     "end": "1.759"
    },
    {
     "start": "2.450",
     "end": "2.532"
    },
    {
     "start": "3.420",
     "end": "3.504"
    },
    {
     "start": "4.406",
     "end": "4.486"
    },
    {
     "start": "5.402",
     "end": "5.486"
    },
    {
     "start": "6.383",
     "end": "6.464"
    },
    {
     "start": "7.366",
     "end": "7.443"
    },
    {
     "start": "8.331",
     "end": "8.416"
    },
    {
     "start": "9.287",
     "end": "9.367"
    },
    {
     "start": "10.250",
     "end": "10.329"
    },
    {
     "start": "11.215",
     "end": "11.294"
    },
    {
     "start": "12.215",
     "end": "12.306"
    },
    {
     "start": "13.208",
     "end": "13.287"
    },
    {
     "start": "14.205",
     "end": "14.289"
    },
    {
     "start": "15.187",
     "end": "15.264"
    },
    {
     "start": "16.184",
     "end": "16.280"
    },
    {
     "start": "17.186",
     "end": "17.275"
    },
    {
     "start": "18.163",
     "end": "18.249"
    },
    {
     "start": "19.128",
     "end": "19.215"
    },
    {
     "start": "20.105",
     "end": "20.185"
    }
   ],
   "S2": [
    {
     "start": "1.007",
     "end": "1.106"
    },
    {
     "start": "0.042",
     "end": "0.128"
    },
    {
     "start": "1.983",
     "end": "2.070"
    },
    {
     "start": "2.761",
     "end": "2.843"
    },
    {
     "start": "3.722",
     "end": "3.813"
    },
    {
     "start": "4.724",
     "end": "4.808"
    },
    {
     "start": "5.719",
     "end": "5.796"
    },
    {
     "start": "6.708",
     "end": "6.784"
    },
    {
     "start": "7.684",
     "end": "7.771"
    },
    {
     "start": "8.644",
     "end": "8.729"
    },
    {
     "start": "9.602",
     "end": "9.682"
    },
    {
     "start": "10.569",
     "end": "10.658"
    },
    {
     "start": "11.546",
     "end": "11.631"
    },
    {
     "start": "12.530",
     "end": "12.616"
    },
    {
     "start": "13.527",
     "end": "13.607"
    },
    {
     "start": "14.509",
     "end": "14.593"
    },
    {
     "start": "15.502",
     "end": "15.586"
    },
    {
     "start": "16.511",
     "end": "16.600"
    },
    {
     "start": "17.506",
     "end": "17.590"
    },
    {
     "start": "18.472",
     "end": "18.560"
    },
    {
     "start": "19.446",
     "end": "19.537"
    },
    {
     "start": "20.410",
     "end": "20.496"
    }
   ],
   "syslole": [
    {
     "start": "0.780",
     "end": "1.007"
    },
    {
     "start": "1.759",
     "end": "1.983"
    },
    {
     "start": "2.532",
     "end": "2.761"
    },
    {
     "start": "3.504",
     "end": "3.722"
    },
    {
     "start": "4.486",
     "end": "4.724"
    },
    {
     "start": "5.486",
     "end": "5.719"
    },
    {
     "start": "6.464",
     "end": "6.708"
    },
    {
     "start": "7.443",
     "end": "7.684"
    },
    {
     "start": "8.416",
     "end": "8.644"
    },
    {
     "start": "9.367",
     "end": "9.602"
    },
    {
     "start": "10.329",
     "end": "10.569"
    },
    {
     "start": "11.294",
     "end": "11.546"
    },
    {
     "start": "12.306",
     "end": "12.530"
    },
    {
     "start": "13.287",
     "end": "13.527"
    },
    {
     "start": "14.289",
     "end": "14.509"
    },
    {
     "start": "15.264",
     "end": "15.502"
    },
    {
     "start": "16.280",
     "end": "16.511"
    },
    {
     "start": "17.275",
     "end": "17.506"
    },
    {
     "start": "18.249",
     "end": "18.472"
    },
    {
     "start": "19.215",
     "end": "19.446"
    },
    {
     "start": "20.185",
     "end": "20.410"
    }
   ],
   "diastole": [
    {
     "start": "0.128",
     "end": "0.690"
    },
    {
     "start": "1.106",
     "end": "1.680"
    },
    {
     "start": "2.070",
     "end": "2.450"
    },
    {
     "start": "2.843",
     "end": "3.420"
    },
    {
     "start": "3.813",
     "end": "4.406"
    },
    {
     "start": "4.808",
     "end": "5.402"
    },
    {
     "start": "5.796",
     "end": "6.383"
    },
    {
     "start": "6.784",
     "end": "7.366"
    },
    {
     "start": "7.771",
     "end": "8.331"
    },
    {
     "start": "8.729",
     "end": "9.287"
    },
    {
     "start": "9.682",
     "end": "10.250"
    },
    {
     "start": "10.658",
     "end": "11.215"
    },
    {
     "start": "11.631",
     "end": "12.215"
    },
    {
     "start": "12.616",
     "end": "13.208"
    },
    {
     "start": "13.607",
     "end": "14.205"
    },
    {
     "start": "14.593",
     "end": "15.187"
    },
    {
     "start": "15.586",
     "end": "16.184"
    },
    {
     "start": "16.600",
     "end": "17.186"
    },
    {
     "start": "17.590",
     "end": "18.163"
    },
    {
     "start": "18.560",
     "end": "19.128"
    },
    {
     "start": "19.537",
     "end": "20.105"
    }
   ],
   "unsegmentable": [
    {
     "start": "0.000",
     "end": "0.042"
    },
    {
     "start": "20.496",
     "end": "20.712"
    }
   ]
  },
  "systolicMurmurs": true,
  "diastolicMurmurs": true,
  "constantMurmurs": false
 },
 {
  "id": "P_Pulmonary_regurgitation_15.wav",
  "bodySpot": "Pulmonic area",
  "segmenation": {
   "S1": [
    {
     "start": "0.753",
     "end": "0.827"
    },
    {
     "start": "1.764",
     "end": "1.840"
    },
    {
     "start": "2.755",
     "end": "2.829"
    },
    {
     "start": "3.728",
     "end": "3.806"
    },
    {
     "start": "4.691",
     "end": "4.770"
    },
    {
     "start": "5.677",
     "end": "5.756"
    },
    {
     "start": "6.449",
     "end": "6.530"
    },
    {
     "start": "7.415",
     "end": "7.497"
    },
    {
     "start": "8.414",
     "end": "8.492"
    },
    {
     "start": "9.401",
     "end": "9.482"
    },
    {
     "start": "10.387",
     "end": "10.464"
    },
    {
     "start": "11.363",
     "end": "11.440"
    },
    {
     "start": "12.330",
     "end": "12.415"
    },
    {
     "start": "13.281",
     "end": "13.361"
    },
    {
     "start": "14.249",
     "end": "14.327"
    },
    {
     "start": "15.209",
     "end": "15.295"
    },
    {
     "start": "16.209",
     "end": "16.288"
    },
    {
     "start": "17.226",
     "end": "17.305"
    },
    {
     "start": "18.199",
     "end": "18.279"
    },
    {
     "start": "19.177",
     "end": "19.260"
    },
    {
     "start": "20.193",
     "end": "20.274"
    }
   ],
   "S2": [
    {
     "start": "0.077",
     "end": "0.154"
    },
    {
     "start": "1.071",
     "end": "1.139"
    },
    {
     "start": "2.077",
     "end": "2.153"
    },
    {
     "start": "3.071",
     "end": "3.145"
    },
    {
     "start": "4.042",
     "end": "4.115"
    },
    {
     "start": "5.005",
     "end": "5.089"
    },
    {
     "start": "5.982",
     "end": "6.060"
    },
    {
     "start": "6.761",
     "end": "6.835"
    },
    {
     "start": "7.724",
     "end": "7.808"
    },
    {
     "start": "8.722",
     "end": "8.800"
    },
    {
     "start": "9.717",
     "end": "9.792"
    },
    {
     "start": "10.707",
     "end": "10.779"
    },
    {
     "start": "11.683",
     "end": "11.768"
    },
    {
     "start": "12.644",
     "end": "12.714"
    },
    {
     "start": "13.597",
     "end": "13.681"
    },
    {
     "start": "14.563",
     "end": "14.639"
    },
    {
     "start": "15.551",
     "end": "15.628"
    },
    {
     "start": "16.534",
     "end": "16.615"
    },
    {
     "start": "17.523",
     "end": "17.612"
    },
    {
     "start": "18.503",
     "end": "18.595"
    },
    {
     "start": "19.504",
     "end": "19.582"
    },
    {
     "start": "20.502",
     "end": "20.587"
    }
   ],
   "syslole": [
    {
     "start": "0.827",
     "end": "1.071"
    },
    {
     "start": "1.840",
     "end": "2.077"
    },
    {
     "start": "2.829",
     "end": "3.071"
    },
    {
     "start": "3.806",
     "end": "4.042"
    },
    {
     "start": "4.770",
     "end": "5.005"
    },
    {
     "start": "5.756",
     "end": "5.982"
    },
    {
     "start": "6.530",
     "end": "6.761"
    },
    {
     "start": "7.497",
     "end": "7.724"
    },
    {
     "start": "8.492",
     "end": "8.722"
    },
    {
     "start": "9.482",
     "end": "9.717"
    },
    {
     "start": "10.464",
     "end": "10.707"
    },
    {
     "start": "11.440",
     "end": "11.683"
    },
    {
     "start": "12.415",
     "end": "12.644"
    },
    {
     "start": "13.361",
     "end": "13.597"
    },
    {
     "start": "14.327",
     "end": "14.563"
    },
    {
     "start": "15.295",
     "end": "15.551"
    },
    {
     "start": "16.288",
     "end": "16.534"
    },
    {
     "start": "17.305",
     "end": "17.523"
    },
    {
     "start": "18.279",
     "end": "18.503"
    },
    {
     "start": "19.260",
     "end": "19.504"
    },
    {
     "start": "20.274",
     "end": "20.502"
    }
   ],
   "diastole": [
    {
     "start": "0.154",
     "end": "0.753"
    },
    {
     "start": "1.139",
     "end": "1.764"
    },
    {
     "start": "2.153",
     "end": "2.755"
    },
    {
     "start": "3.145",
     "end": "3.728"
    },
    {
     "start": "4.115",
     "end": "4.691"
    },
    {
     "start": "5.089",
     "end": "5.677"
    },
    {
     "start": "6.060",
     "end": "6.449"
    },
    {
     "start": "6.835",
     "end": "7.415"
    },
    {
     "start": "7.808",
     "end": "8.414"
    },
    {
     "start": "8.800",
     "end": "9.401"
    },
    {
     "start": "9.792",
     "end": "10.387"
    },
    {
     "start": "10.779",
     "end": "11.363"
    },
    {
     "start": "11.768",
     "end": "12.330"
    },
    {
     "start": "12.714",
     "end": "13.281"
    },
    {
     "start": "13.681",
     "end": "14.249"
    },
    {
     "start": "14.639",
     "end": "15.209"
    },
    {
     "start": "15.628",
     "end": "16.209"
    },
    {
     "start": "16.615",
     "end": "17.226"
    },
    {
     "start": "17.612",
     "end": "18.199"
    },
    {
     "start": "18.595",
     "end": "19.177"
    },
    {
     "start": "19.582",
     "end": "20.193"
    }
   ],
   "unsegmentable": [
    {
     "start": "0.000",
     "end": "0.077"
    },
    {
     "start": "20.587",
     "end": "20.944"
    }
   ]
  },
  "systolicMurmurs": true,
  "diastolicMurmurs": true,
  "constantMurmurs": false
 },
 {
  "id": "P_Pulmonary_regurgitation_4.wav",
  "bodySpot": "Pulmonic area",
  "segmenation": {
   "S1": [
    {
     "start": "0.984",
     "end": "1.072"
    },
    {
     "start": "0.015",
     "end": "0.099"
    },
    {
     "start": "1.934",
     "end": "2.031"
    },
    {
     "start": "2.897",
     "end": "2.985"
    },
    {
     "start": "3.852",
     "end": "3.942"
    },
    {
     "start": "4.828",
     "end": "4.922"
    },
    {
     "start": "5.822",
     "end": "5.916"
    },
    {
     "start": "6.837",
     "end": "6.934"
    },
    {
     "start": "7.815",
     "end": "7.909"
    },
    {
     "start": "8.780",
     "end": "8.878"
    },
    {
     "start": "9.801",
     "end": "9.900"
    },
    {
     "start": "10.790",
     "end": "10.886"
    },
    {
     "start": "11.773",
     "end": "11.872"
    },
    {
     "start": "12.741",
     "end": "12.831"
    },
    {
     "start": "13.708",
     "end": "13.802"
    },
    {
     "start": "14.486",
     "end": "14.585"
    },
    {
     "start": "15.535",
     "end": "15.625"
    },
    {
     "start": "16.525",
     "end": "16.626"
    },
    {
     "start": "17.526",
     "end": "17.614"
    },
    {
     "start": "18.520",
     "end": "18.610"
    },
    {
     "start": "19.487",
     "end": "19.576"
    },
    {
     "start": "20.453",
     "end": "20.543"
    }
   ],
   "S2": [
    {
     "start": "1.291",
     "end": "1.374"
    },
    {
     "start": "0.319",
     "end": "0.403"
    },
    {
     "start": "2.257",
     "end": "2.354"
    },
    {
     "start": "3.214",
     "end": "3.306"
    },
    {
     "start": "4.175",
     "end": "4.267"
    },
    {
     "start": "5.148",
     "end": "5.246"
    },
    {
     "start": "6.130",
     "end": "6.233"
    },
    {
     "start": "7.139",
     "end": "7.234"
    },
    {
     "start": "8.125",
     "end": "8.213"
    },
    {
     "start": "9.113",
     "end": "9.216"
    },
    {
     "start": "10.127",
     "end": "10.217"
    },
    {
     "start": "11.115",
     "end": "11.217"
    },
    {
     "start": "12.080",
     "end": "12.180"
    },
    {
     "start": "13.053",
     "end": "13.158"
    },
    {
     "start": "14.018",
     "end": "14.117"
    },
    {
     "start": "14.803",
     "end": "14.891"
    },
    {
     "start": "15.854",
     "end": "15.952"
    },
    {
     "start": "16.842",
     "end": "16.936"
    },
    {
     "start": "17.834",
     "end": "17.922"
    },
    {
     "start": "18.835",
     "end": "18.929"
    },
    {
     "start": "19.817",
     "end": "19.905"
    }
   ],
   "syslole": [
    {
     "start": "0.099",
     "end": "0.319"
    },
    {
     "start": "1.072",
     "end": "1.291"
    },
    {
     "start": "2.031",
     "end": "2.257"
    },
    {
     "start": "2.985",
     "end": "3.214"
    },
    {
     "start": "3.942",
     "end": "4.175"
    },
    {
     "start": "4.922",
     "end": "5.148"
    },
    {
     "start": "5.916",
     "end": "6.130"
    },
    {
     "start": "6.934",
     "end": "7.139"
    },
    {
     "start": "7.909",
     "end": "8.125"
    },
    {
     "start": "8.878",
     "end": "9.113"
    },
    {
     "start": "9.900",
     "end": "10.127"
    },
    {
     "start": "10.886",
     "end": "11.115"
    },
    {
     "start": "11.872",
     "end": "12.080"
    },
    {
     "start": "12.831",
     "end": "13.053"
    },
    {
     "start": "13.802",
     "end": "14.018"
    },
    {
     "start": "14.585",
     "end": "14.803"
    },
    {
     "start": "15.625",
     "end": "15.854"
    },
    {
     "start": "16.626",
     "end": "16.842"
    },
    {
     "start": "17.614",
     "end": "17.834"
    },
    {
     "start": "18.610",
     "end": "18.835"
    },
    {
     "start": "19.576",
     "end": "19.817"
    }
   ],
   "diastole": [
    {
     "start": "0.403",
     "end": "0.984"
    },
    {
     "start": "1.374",
     "end": "1.934"
    },
    {
     "start": "2.354",
     "end": "2.897"
    },
    {
     "start": "3.306",
     "end": "3.852"
    },
    {
     "start": "4.267",
     "end": "4.828"
    },
    {
     "start": "5.246",
     "end": "5.822"
    },
    {
     "start": "6.233",
     "end": "6.837"
    },
    {
     "start": "7.234",
     "end": "7.815"
    },
    {
     "start": "8.213",
     "end": "8.780"
    },
    {
     "start": "9.216",
     "end": "9.801"
    },
    {
     "start": "10.217",
     "end": "10.790"
    },
    {
     "start": "11.217",
     "end": "11.773"
    },
    {
     "start": "12.180",
     "end": "12.741"
    },
    {
     "start": "13.158",
     "end": "13.708"
    },
    {
     "start": "14.117",
     "end": "14.486"
    },
    {
     "start": "14.891",
     "end": "15.535"
    },
    {
     "start": "15.952",
     "end": "16.525"
    },
    {
     "start": "16.936",
     "end": "17.526"
    },
    {
     "start": "17.922",
     "end": "18.520"
    },
    {
     "start": "18.929",
     "end": "19.487"
    },
    {
     "start": "19.905",
     "end": "20.453"
    }
   ],
   "unsegmentable": [
    {
     "start": "0.000",
     "end": "0.015"
    },
    {
     "start": "20.543",
     "end": "20.643"
    }
   ]
  },
  "systolicMurmurs": true,
  "diastolicMurmurs": true,
  "constantMurmurs": false
 },
 {
  "id": "P_Pulmonary_regurgitation_8.wav",
  "bodySpot": "Pulmonic area",
  "segmenation": {
   "S1": [
    {
     "start": "0.652",
     "end": "0.713"
    },
    {
     "start": "2.140",
     "end": "2.215"
    },
    {
     "start": "3.139",
     "end": "3.223"
    },
    {
     "start": "4.143",
     "end": "4.212"
    },
    {
     "start": "5.113",
     "end": "5.195"
    },
    {
     "start": "6.106",
     "end": "6.169"
    },
    {
     "start": "7.052",
     "end": "7.127"
    },
    {
     "start": "8.018",
     "end": "8.072"
    },
    {
     "start": "8.983",
     "end": "9.051"
    },
    {
     "start": "9.956",
     "end": "10.034"
    },
    {
     "start": "10.951",
     "end": "11.020"
    },
    {
     "start": "11.992",
     "end": "12.050"
    },
    {
     "start": "12.933",
     "end": "13.001"
    },
    {
     "start": "13.914",
     "end": "13.991"
    },
    {
     "start": "14.923",
     "end": "15.001"
    },
    {
     "start": "15.920",
     "end": "16.001"
    },
    {
     "start": "16.890",
     "end": "16.973"
    },
    {
     "start": "17.861",
     "end": "17.941"
    },
    {
     "start": "18.847",
     "end": "18.920"
    },
    {
     "start": "19.613",
     "end": "19.698"
    },
    {
     "start": "20.580",
     "end": "20.655"
    }
   ],
   "S2": [
    {
     "start": "0.950",
     "end": "1.020"
    },
    {
     "start": "2.449",
     "end": "2.514"
    },
    {
     "start": "3.451",
     "end": "3.522"
    },
    {
     "start": "4.442",
     "end": "4.516"
    },
    {
     "start": "5.432",
     "end": "5.502"
    },
    {
     "start": "6.408",
     "end": "6.468"
    },
    {
     "start": "7.366",
     "end": "7.433"
    },
    {
     "start": "8.299",
     "end": "8.360"
    },
    {
     "start": "9.289",
     "end": "9.360"
    },
    {
     "start": "10.271",
     "end": "10.349"
    },
    {
     "start": "11.256",
     "end": "11.332"
    },
    {
     "start": "12.263",
     "end": "12.320"
    },
    {
     "start": "13.241",
     "end": "13.314"
    },
    {
     "start": "14.235",
     "end": "14.314"
    },
    {
     "start": "15.234",
     "end": "15.313"
    },
    {
     "start": "16.231",
     "end": "16.310"
    },
    {
     "start": "17.202",
     "end": "17.282"
    },
    {
     "start": "18.171",
     "end": "18.231"
    },
    {
     "start": "19.139",
     "end": "19.220"
    },
    {
     "start": "19.929",
     "end": "20.008"
    },
    {
     "start": "0.023",
     "end": "0.120"
    }
   ],
   "syslole": [
    {
     "start": "0.713",
     "end": "0.950"
    },
    {
     "start": "2.215",
     "end": "2.449"
    },
    {
     "start": "3.223",
     "end": "3.451"
    },
    {
     "start": "4.212",
     "end": "4.442"
    },
    {
     "start": "5.195",
     "end": "5.432"
    },
    {
     "start": "6.169",
     "end": "6.408"
    },
    {
     "start": "7.127",
     "end": "7.366"
    },
    {
     "start": "8.072",
     "end": "8.299"
    },
    {
     "start": "9.051",
     "end": "9.289"
    },
    {
     "start": "10.034",
     "end": "10.271"
    },
    {
     "start": "11.020",
     "end": "11.256"
    },
    {
     "start": "12.050",
     "end": "12.263"
    },
    {
     "start": "13.001",
     "end": "13.241"
    },
    {
     "start": "13.991",
     "end": "14.235"
    },
    {
     "start": "15.001",
     "end": "15.234"
    },
    {
     "start": "16.001",
     "end": "16.231"
    },
    {
     "start": "16.973",
     "end": "17.202"
    },
    {
     "start": "17.941",
     "end": "18.171"
    },
    {
     "start": "18.920",
     "end": "19.139"
    },
    {
     "start": "19.698",
     "end": "19.929"
    }
   ],
   "diastole": [
    {
     "start": "0.120",
     "end": "0.652"
    },
    {
     "start": "1.020",
     "end": "2.140"
    },
    {
     "start": "2.514",
     "end": "3.139"
    },
    {
     "start": "3.522",
     "end": "4.143"
    },
    {
     "start": "4.516",
     "end": "5.113"
    },
    {
     "start": "5.502",
     "end": "6.106"
    },
    {
     "start": "6.468",
     "end": "7.052"
    },
    {
     "start": "7.433",
     "end": "8.018"
    },
    {
     "start": "8.360",
     "end": "8.983"
    },
    {
     "start": "9.360",
     "end": "9.956"
    },
    {
     "start": "10.349",
     "end": "10.951"
    },
    {
     "start": "11.332",
     "end": "11.992"
    },
    {
     "start": "12.320",
     "end": "12.933"
    },
    {
     "start": "13.314",
     "end": "13.914"
    },
    {
     "start": "14.314",
     "end": "14.923"
    },
    {
     "start": "15.313",
     "end": "15.920"
    },
    {
     "start": "16.310",
     "end": "16.890"
    },
    {
     "start": "17.282",
     "end": "17.861"
    },
    {
     "start": "18.231",
     "end": "18.847"
    },
    {
     "start": "19.220",
     "end": "19.613"
    },
    {
     "start": "20.008",
     "end": "20.580"
    }
   ],
   "unsegmentable": [
    {
     "start": "0.000",
     "end": "0.023"
    }
   ]
  },
  "systolicMurmurs": true,
  "diastolicMurmurs": true,
  "constantMurmurs": false
 },
 {
  "id": "P_Pulmonary_regurgitation_9.wav",
  "bodySpot": "Pulmonic area",
  "segmenation": {
   "S1": [
    {
     "start": "2.162",
     "end": "2.244"
    },
    {
     "start": "13.853",
     "end": "13.940"
    },
    {
     "start": "14.529",
     "end": "14.621"
    },
    {
     "start": "15.202",
     "end": "15.281"
    },
    {
     "start": "15.871",
     "end": "15.963"
    },
    {
     "start": "16.540",
     "end": "16.637"
    },
    {
     "start": "17.199",
     "end": "17.302"
    },
    {
     "start": "17.939",
     "end": "18.009"
    },
    {
     "start": "18.566",
     "end": "18.661"
    },
    {
     "start": "19.238",
     "end": "19.339"
    },
    {
     "start": "20.601",
     "end": "20.679"
    },
    {
     "start": "19.925",
     "end": "20.002"
    },
    {
     "start": "21.240",
     "end": "21.318"
    },
    {
     "start": "9.737",
     "end": "9.834"
    },
    {
     "start": "9.054",
     "end": "9.147"
    },
    {
     "start": "8.362",
     "end": "8.453"
    },
    {
     "start": "7.684",
     "end": "7.764"
    },
    {
     "start": "6.983",
     "end": "7.072"
    },
    {
     "start": "2.840",
     "end": "2.935"
    },
    {
     "start": "3.535",
     "end": "3.630"
    },
    {
     "start": "4.236",
     "end": "4.325"
    },
    {
     "start": "6.281",
     "end": "6.367"
    },
    {
     "start": "5.621",
     "end": "5.700"
    },
    {
     "start": "13.204",
     "end": "13.280"
    },
    {
     "start": "12.543",
     "end": "12.613"
    },
    {
     "start": "11.839",
     "end": "11.917"
    },
    {
     "start": "11.151",
     "end": "11.232"
    },
    {
     "start": "10.462",
     "end": "10.538"
    },
    {
     "start": "1.470",
     "end": "1.559"
    },
    {
     "start": "0.767",
     "end": "0.864"
    },
    {
     "start": "0.092",
     "end": "0.184"
    },
    {
     "start": "4.902",
     "end": "4.994"
    }
   ],
   "S2": [
    {
     "start": "2.472",
     "end": "2.572"
    },
    {
     "start": "14.181",
     "end": "14.287"
    },
    {
     "start": "14.860",
     "end": "14.958"
    },
    {
     "start": "15.510",
     "end": "15.634"
    },
    {
     "start": "16.195",
     "end": "16.316"
    },
    {
     "start": "16.865",
     "end": "16.973"
    },
    {
     "start": "17.537",
     "end": "17.654"
    },
    {
     "start": "18.229",
     "end": "18.347"
    },
    {
     "start": "18.904",
     "end": "19.008"
    },
    {
     "start": "19.565",
     "end": "19.673"
    },
    {
     "start": "20.916",
     "end": "21.033"
    },
    {
     "start": "20.233",
     "end": "20.362"
    },
    {
     "start": "10.075",
     "end": "10.179"
    },
    {
     "start": "10.762",
     "end": "10.881"
    },
    {
     "start": "13.507",
     "end": "13.622"
    },
    {
     "start": "12.837",
     "end": "12.940"
    },
    {
     "start": "12.142",
     "end": "12.245"
    },
    {
     "start": "11.459",
     "end": "11.569"
    },
    {
     "start": "9.392",
     "end": "9.495"
    },
    {
     "start": "8.679",
     "end": "8.802"
    },
    {
     "start": "7.990",
     "end": "8.115"
    },
    {
     "start": "7.293",
     "end": "7.390"
    },
    {
     "start": "3.149",
     "end": "3.263"
    },
    {
     "start": "1.792",
     "end": "1.888"
    },
    {
     "start": "3.864",
     "end": "3.959"
    },
    {
     "start": "4.545",
     "end": "4.642"
    },
    {
     "start": "6.609",
     "end": "6.712"
    },
    {
     "start": "5.925",
     "end": "6.031"
    },
    {
     "start": "1.098",
     "end": "1.207"
    },
    {
     "start": "0.422",
     "end": "0.508"
    },
    {
     "start": "5.222",
     "end": "5.334"
    }
   ],
   "syslole": [
    {
     "start": "0.184",
     "end": "0.422"
    },
    {
     "start": "0.864",
     "end": "1.098"
    },
    {
     "start": "1.559",
     "end": "1.792"
    },
    {
     "start": "2.244",
     "end": "2.472"
    },
    {
     "start": "2.935",
     "end": "3.149"
    },
    {
     "start": "3.630",
     "end": "3.864"
    },
    {
     "start": "4.325",
     "end": "4.545"
    },
    {
     "start": "4.994",
     "end": "5.222"
    },
    {
     "start": "5.700",
     "end": "5.925"
    },
    {
     "start": "6.367",
     "end": "6.609"
    },
    {
     "start": "7.072",
     "end": "7.293"
    },
    {
     "start": "7.764",
     "end": "7.990"
    },
    {
     "start": "8.453",
     "end": "8.679"
    },
    {
     "start": "9.147",
     "end": "9.392"
    },
    {
     "start": "9.834",
     "end": "10.075"
    },
    {
     "start": "10.538",
     "end": "10.762"
    },
    {
     "start": "11.232",
     "end": "11.459"
    },
    {
     "start": "11.917",
     "end": "12.142"
    },
    {
     "start": "12.613",
     "end": "12.837"
    },
    {
     "start": "13.280",
     "end": "13.507"
    },
    {
     "start": "13.940",
     "end": "14.181"
    },
    {
     "start": "14.621",
     "end": "14.860"
    },
    {
     "start": "15.281",
     "end": "15.510"
    },
    {
     "start": "15.963",
     "end": "16.195"
    },
    {
     "start": "16.637",
     "end": "16.865"
    },
    {
     "start": "17.302",
     "end": "17.537"
    },
    {
     "start": "18.009",
     "end": "18.229"
    },
    {
     "start": "18.661",
     "end": "18.904"
    },
    {
     "start": "19.339",
     "end": "19.565"
    },
    {
     "start": "20.002",
     "end": "20.233"
    },
    {
     "start": "20.679",
     "end": "20.916"
    }
   ],
   "diastole": [
    {
     "start": "0.508",
     "end": "0.767"
    },
    {
     "start": "1.207",
     "end": "1.470"
    },
    {
     "start": "1.888",
     "end": "2.162"
    },
    {
     "start": "2.572",
     "end": "2.840"
    },
    {
     "start": "3.263",
     "end": "3.535"
    },
    {
     "start": "3.959",
     "end": "4.236"
    },
    {
     "start": "4.642",
     "end": "4.902"
    },
    {
     "start": "5.334",
     "end": "5.621"
    },
    {
     "start": "6.031",
     "end": "6.281"
    },
    {
     "start": "6.712",
     "end": "6.983"
    },
    {
     "start": "7.390",
     "end": "7.684"
    },
    {
     "start": "8.115",
     "end": "8.362"
    },
    {
     "start": "8.802",
     "end": "9.054"
    },
    {
     "start": "9.495",
     "end": "9.737"
    },
    {
     "start": "10.179",
     "end": "10.462"
    },
    {
     "start": "10.881",
     "end": "11.151"
    },
    {
     "start": "11.569",
     "end": "11.839"
    },
    {
     "start": "12.245",
     "end": "12.543"
    },
    {
     "start": "12.940",
     "end": "13.204"
    },
    {
     "start": "13.622",
     "end": "13.853"
    },
    {
     "start": "14.287",
     "end": "14.529"
    },
    {
     "start": "14.958",
     "end": "15.202"
    },
    {
     "start": "15.634",
     "end": "15.871"
    },
    {
     "start": "16.316",
     "end": "16.540"
    },
    {
     "start": "16.973",
     "end": "17.199"
    },
    {
     "start": "17.654",
     "end": "17.939"
    },
    {
     "start": "18.347",
     "end": "18.566"
    },
    {
     "start": "19.008",
     "end": "19.238"
    },
    {
     "start": "19.673",
     "end": "19.925"
    },
    {
     "start": "20.362",
     "end": "20.601"
    },
    {
     "start": "21.033",
     "end": "21.240"
    }
   ],
   "unsegmentable": [
    {
     "start": "0.000",
     "end": "0.092"
    },
    {
     "start": "21.318",
     "end": "21.339"
    }
   ]
  },
  "systolicMurmurs": false,
  "diastolicMurmurs": false,
  "constantMurmurs": false
 }
]